finn_ingestion_lib/__init__.py
finn_ingestion_lib/finn_ingestion_lib.py
finn_ingestion_lib-0.0.6.dist-info/METADATA
finn_ingestion_lib-0.0.6.dist-info/WHEEL
finn_ingestion_lib-0.0.6.dist-info/top_level.txt
finn_ingestion_lib-0.0.6.dist-info/RECORD
